pyarchi/__init__.py
pyarchi/data_objects/Data.py
pyarchi/data_objects/Mask.py
pyarchi/data_objects/Star_class.py
pyarchi/data_objects/__init__.py
pyarchi/initial_detection/__init__.py
pyarchi/initial_detection/dynam_method.py
pyarchi/initial_detection/fits_method.py
pyarchi/masks_creation/__init__.py
pyarchi/masks_creation/circular_mask.py
pyarchi/masks_creation/grid_conversion.py
pyarchi/masks_creation/shape_mask.py
pyarchi/output_creation/__init__.py
pyarchi/output_creation/photometry_outputs.py
pyarchi/output_creation/storage_handler.py
pyarchi/routines/Photo_Controller.py
pyarchi/routines/__init__.py
pyarchi/routines/photometric_process.py
pyarchi/star_track/__init__.py
pyarchi/star_track/dynamical_centers.py
pyarchi/star_track/offset_centers.py
pyarchi/star_track/star_tracking_handler.py
pyarchi/star_track/static_method.py
pyarchi/utils/__init__.py
pyarchi/utils/data_export/__init__.py
pyarchi/utils/data_export/export_fits.py
pyarchi/utils/data_export/export_photo_info.py
pyarchi/utils/data_export/export_txt.py
pyarchi/utils/data_export/folder_handler.py
pyarchi/utils/factors_handler/__init__.py
pyarchi/utils/factors_handler/factors_handlers.py
pyarchi/utils/image_processing/__init__.py
pyarchi/utils/image_processing/calculate_moments.py
pyarchi/utils/image_processing/shape_analysis.py
pyarchi/utils/image_processing/shape_increase.py
pyarchi/utils/misc/__init__.py
pyarchi/utils/misc/create_gif.py
pyarchi/utils/misc/logger_setup.py
pyarchi/utils/misc/parameters_validator.py
pyarchi/utils/misc/path_searcher.py
pyarchi/utils/misc/rotation_mats.py
pyarchi/utils/misc/timer.py
pyarchi/utils/noise_metrics/CDPP.py
pyarchi/utils/noise_metrics/__init__.py
pyarchi/utils/optimization/__init__.py
pyarchi/utils/optimization/circular_fine_tune.py
pyarchi/utils/optimization/optimizer.py
pyarchi/utils/optimization/threaded_optimization.py
pyarchi-1.2.1.dist-info/LICENSE
pyarchi-1.2.1.dist-info/WHEEL
pyarchi-1.2.1.dist-info/METADATA
pyarchi-1.2.1.dist-info/RECORD
