Metadata-Version: 2.1
Name: pyarchi
Version: 1.2.1
Summary: Photometry for CHEOPS's background stars
Home-page: https://github.com/Kamuish/archi
Author: Kamuish
Author-email: amiguel@astro.up.pt
Requires-Python: >=3.6,<4.0
Classifier: Programming Language :: Python :: 3
Classifier: Programming Language :: Python :: 3.6
Classifier: Programming Language :: Python :: 3.7
Classifier: Programming Language :: Python :: 3.8
Requires-Dist: astropy (>=4.0,<5.0)
Requires-Dist: imageio (>=2.8.0,<3.0.0)
Requires-Dist: matplotlib (>=3.1.2,<4.0.0)
Requires-Dist: opencv-python (>=4.1.2,<5.0.0)
Requires-Dist: pyyaml (>=5.3,<6.0)
Requires-Dist: scipy (>=1.4.1,<2.0.0)
Project-URL: Documentation, https://archi.readthedocs.io/en/latest/
Project-URL: Repository, https://github.com/Kamuish/archi
